postfix_stats.py
setup.py
postfix_stats.egg-info/PKG-INFO
postfix_stats.egg-info/SOURCES.txt
postfix_stats.egg-info/dependency_links.txt
postfix_stats.egg-info/not-zip-safe
postfix_stats.egg-info/top_level.txt