Metadata-Version: 1.1
Name: postfix-stats
Version: 0.2.0
Summary: Simple threaded stats aggregator for Postfix. When running as a syslog destination, it can be used to get realtime cumulative stats.
Home-page: http://github.com/disqus/postfix-stats
Author: DISQUS
Author-email: opensource@disqus.com
License: Apache License 2.0
Keywords: postfix stats
Platform: UNKNOWN
Classifier: Development Status :: 5 - Production/Stable
Classifier: Intended Audience :: Developers
Classifier: Intended Audience :: System Administrators
Classifier: Operating System :: OS Independent
Classifier: Topic :: Software Development
Classifier: Topic :: Communications :: Email :: Mail Transport Agents
Classifier: Topic :: System :: Monitoring
